{"__type__":"cc.JsonAsset","_name":"Level","json":{"1":{"ID":1,"Name":"炼气期(一层)","ExpMin":0,"ExpMax":10,"Awards":[10008,10009],"Counts":[1,1],"NeedType":[0],"Monsters":[0]},"2":{"ID":2,"Name":"炼气期(二层)","ExpMin":11,"ExpMax":30,"Awards":[10008,10009],"Counts":[2,1],"NeedType":[0],"Monsters":[0]},"3":{"ID":3,"Name":"炼气期(三层)","ExpMin":31,"ExpMax":60,"Awards":[10008,10009],"Counts":[3,1],"NeedType":[0],"Monsters":[0]},"4":{"ID":4,"Name":"炼气期(四层)","ExpMin":61,"ExpMax":110,"Awards":[10008,10009],"Counts":[4,1],"NeedType":[0],"Monsters":[0]},"5":{"ID":5,"Name":"炼气期(五层)","ExpMin":111,"ExpMax":180,"Awards":[10008,10009],"Counts":[5,1],"NeedType":[0],"Monsters":[0]},"6":{"ID":6,"Name":"炼气期(六层)","ExpMin":181,"ExpMax":270,"Awards":[10008,10009],"Counts":[6,1],"NeedType":[0],"Monsters":[0]},"7":{"ID":7,"Name":"炼气期(七层)","ExpMin":271,"ExpMax":390,"Awards":[10008,10009],"Counts":[7,1],"NeedType":[0],"Monsters":[0]},"8":{"ID":8,"Name":"炼气期(八层)","ExpMin":391,"ExpMax":540,"Awards":[10008,10009],"Counts":[8,1],"NeedType":[0],"Monsters":[0]},"9":{"ID":9,"Name":"炼气期(九层)","ExpMin":541,"ExpMax":720,"Awards":[10008,10009],"Counts":[9,1],"NeedType":[15001,1],"Monsters":[71001]},"10":{"ID":10,"Name":"筑基期(一层)","ExpMin":721,"ExpMax":1000,"Awards":[10008,10009],"Counts":[12,2],"NeedType":[15001,2],"Monsters":[71002]},"11":{"ID":11,"Name":"筑基期(二层)","ExpMin":1001,"ExpMax":1380,"Awards":[10008,10009],"Counts":[13,2],"NeedType":[15001,3],"Monsters":[71003]},"12":{"ID":12,"Name":"筑基期(三层)","ExpMin":1381,"ExpMax":1860,"Awards":[10008,10009],"Counts":[14,2],"NeedType":[15001,4],"Monsters":[71004]},"13":{"ID":13,"Name":"筑基期(四层)","ExpMin":1861,"ExpMax":2540,"Awards":[10008,10009],"Counts":[15,2],"NeedType":[15001,5],"Monsters":[71005]},"14":{"ID":14,"Name":"筑基期(五层)","ExpMin":2541,"ExpMax":3420,"Awards":[10008,10009],"Counts":[16,2],"NeedType":[15001,6],"Monsters":[71006]},"15":{"ID":15,"Name":"筑基期(六层)","ExpMin":3421,"ExpMax":4500,"Awards":[10008,10009],"Counts":[17,2],"NeedType":[15001,7],"Monsters":[71007]},"16":{"ID":16,"Name":"筑基期(七层)","ExpMin":4501,"ExpMax":5880,"Awards":[10008,10009],"Counts":[18,2],"NeedType":[15001,8],"Monsters":[71008]},"17":{"ID":17,"Name":"筑基期(八层)","ExpMin":5881,"ExpMax":7560,"Awards":[10008,10009],"Counts":[19,2],"NeedType":[15001,9],"Monsters":[71009]},"18":{"ID":18,"Name":"筑基期(九层)","ExpMin":7561,"ExpMax":9540,"Awards":[10008,10009],"Counts":[20,2],"NeedType":[15002,1],"Monsters":[71011]},"19":{"ID":19,"Name":"金丹期(一层)","ExpMin":9541,"ExpMax":12520,"Awards":[10008,10009],"Counts":[34,3],"NeedType":[15002,2],"Monsters":[71012]},"20":{"ID":20,"Name":"金丹期(二层)","ExpMin":12521,"ExpMax":16500,"Awards":[10008,10009],"Counts":[35,3],"NeedType":[15002,3],"Monsters":[71013]},"21":{"ID":21,"Name":"金丹期(三层)","ExpMin":16501,"ExpMax":21480,"Awards":[10008,10009],"Counts":[36,3],"NeedType":[15002,4],"Monsters":[71014]},"22":{"ID":22,"Name":"金丹期(四层)","ExpMin":21481,"ExpMax":28460,"Awards":[10008,10009],"Counts":[37,3],"NeedType":[15002,5],"Monsters":[71015]},"23":{"ID":23,"Name":"金丹期(五层)","ExpMin":28461,"ExpMax":37440,"Awards":[10008,10009],"Counts":[38,3],"NeedType":[15002,6],"Monsters":[71016]},"24":{"ID":24,"Name":"金丹期(六层)","ExpMin":37441,"ExpMax":48420,"Awards":[10008,10009],"Counts":[39,3],"NeedType":[15002,7],"Monsters":[71017]},"25":{"ID":25,"Name":"金丹期(七层)","ExpMin":48421,"ExpMax":62400,"Awards":[10008,10009],"Counts":[40,3],"NeedType":[15002,8],"Monsters":[71018]},"26":{"ID":26,"Name":"金丹期(八层)","ExpMin":62401,"ExpMax":79380,"Awards":[10008,10009],"Counts":[41,3],"NeedType":[15002,9],"Monsters":[71019]},"27":{"ID":27,"Name":"金丹期(九层)","ExpMin":79381,"ExpMax":99360,"Awards":[10008,10009],"Counts":[42,3],"NeedType":[15003,1],"Monsters":[71021]},"28":{"ID":28,"Name":"元婴期(一层)","ExpMin":99361,"ExpMax":129340,"Awards":[10008,10009],"Counts":[67,4],"NeedType":[15003,2],"Monsters":[71022]},"29":{"ID":29,"Name":"元婴期(二层)","ExpMin":129341,"ExpMax":169320,"Awards":[10008,10009],"Counts":[68,4],"NeedType":[15003,3],"Monsters":[71023]},"30":{"ID":30,"Name":"元婴期(三层)","ExpMin":169321,"ExpMax":219300,"Awards":[10008,10009],"Counts":[69,4],"NeedType":[15003,4],"Monsters":[71024]},"31":{"ID":31,"Name":"元婴期(四层)","ExpMin":219301,"ExpMax":289280,"Awards":[10008,10009],"Counts":[70,4],"NeedType":[15003,5],"Monsters":[71025]},"32":{"ID":32,"Name":"元婴期(五层)","ExpMin":289281,"ExpMax":379260,"Awards":[10008,10009],"Counts":[71,4],"NeedType":[15003,6],"Monsters":[71026]},"33":{"ID":33,"Name":"元婴期(六层)","ExpMin":379261,"ExpMax":489240,"Awards":[10008,10009],"Counts":[72,4],"NeedType":[15003,7],"Monsters":[71027]},"34":{"ID":34,"Name":"元婴期(七层)","ExpMin":489241,"ExpMax":629220,"Awards":[10008,10009],"Counts":[73,4],"NeedType":[15003,8],"Monsters":[71028]},"35":{"ID":35,"Name":"元婴期(八层)","ExpMin":629221,"ExpMax":799200,"Awards":[10008,10009],"Counts":[74,4],"NeedType":[15003,9],"Monsters":[71029]},"36":{"ID":36,"Name":"元婴期(九层)","ExpMin":799201,"ExpMax":999180,"Awards":[10008,10009],"Counts":[75,4],"NeedType":[15004,1],"Monsters":[71031]},"37":{"ID":37,"Name":"化神期(一层)","ExpMin":999181,"ExpMax":1299160,"Awards":[10008,10009],"Counts":[111,5],"NeedType":[15004,2],"Monsters":[71032]},"38":{"ID":38,"Name":"化神期(二层)","ExpMin":1299161,"ExpMax":1699140,"Awards":[10008,10009],"Counts":[112,5],"NeedType":[15004,3],"Monsters":[71033]},"39":{"ID":39,"Name":"化神期(三层)","ExpMin":1699141,"ExpMax":2199120,"Awards":[10008,10009],"Counts":[113,5],"NeedType":[15004,4],"Monsters":[71034]},"40":{"ID":40,"Name":"化神期(四层)","ExpMin":2199121,"ExpMax":2899100,"Awards":[10008,10009],"Counts":[114,5],"NeedType":[15004,5],"Monsters":[71035]},"41":{"ID":41,"Name":"化神期(五层)","ExpMin":2899101,"ExpMax":3799080,"Awards":[10008,10009],"Counts":[115,5],"NeedType":[15004,6],"Monsters":[71036]},"42":{"ID":42,"Name":"化神期(六层)","ExpMin":3799081,"ExpMax":4899060,"Awards":[10008,10009],"Counts":[116,5],"NeedType":[15004,7],"Monsters":[71037]},"43":{"ID":43,"Name":"化神期(七层)","ExpMin":4899061,"ExpMax":6299040,"Awards":[10008,10009],"Counts":[117,5],"NeedType":[15004,8],"Monsters":[71038]},"44":{"ID":44,"Name":"化神期(八层)","ExpMin":6299041,"ExpMax":7999020,"Awards":[10008,10009],"Counts":[118,5],"NeedType":[15004,9],"Monsters":[71039]},"45":{"ID":45,"Name":"化神期(九层)","ExpMin":7999021,"ExpMax":9999000,"Awards":[10008,10009],"Counts":[119,5],"NeedType":[15005,1],"Monsters":[71041]},"46":{"ID":46,"Name":"合体期(一层)","ExpMin":9999001,"ExpMax":12998980,"Awards":[10008,10009],"Counts":[166,6],"NeedType":[15005,2],"Monsters":[71042]},"47":{"ID":47,"Name":"合体期(二层)","ExpMin":12998981,"ExpMax":16998960,"Awards":[10008,10009],"Counts":[167,6],"NeedType":[15005,3],"Monsters":[71043]},"48":{"ID":48,"Name":"合体期(三层)","ExpMin":16998961,"ExpMax":21998940,"Awards":[10008,10009],"Counts":[168,6],"NeedType":[15005,4],"Monsters":[71044]},"49":{"ID":49,"Name":"合体期(四层)","ExpMin":21998941,"ExpMax":28998920,"Awards":[10008,10009],"Counts":[169,6],"NeedType":[15005,5],"Monsters":[71045]},"50":{"ID":50,"Name":"合体期(五层)","ExpMin":28998921,"ExpMax":37998900,"Awards":[10008,10009],"Counts":[170,6],"NeedType":[15005,6],"Monsters":[71046]},"51":{"ID":51,"Name":"合体期(六层)","ExpMin":37998901,"ExpMax":48998880,"Awards":[10008,10009],"Counts":[171,6],"NeedType":[15005,7],"Monsters":[71047]},"52":{"ID":52,"Name":"合体期(七层)","ExpMin":48998881,"ExpMax":62998860,"Awards":[10008,10009],"Counts":[172,6],"NeedType":[15005,8],"Monsters":[71048]},"53":{"ID":53,"Name":"合体期(八层)","ExpMin":62998861,"ExpMax":79998840,"Awards":[10008,10009],"Counts":[173,6],"NeedType":[15005,9],"Monsters":[71049]},"54":{"ID":54,"Name":"合体期(九层)","ExpMin":79998841,"ExpMax":99998820,"Awards":[10008,10009],"Counts":[174,6],"NeedType":[15006,1],"Monsters":[71051]},"55":{"ID":55,"Name":"大乘期(一层)","ExpMin":99998821,"ExpMax":129998800,"Awards":[10008,10009],"Counts":[232,7],"NeedType":[15006,2],"Monsters":[71052]},"56":{"ID":56,"Name":"大乘期(二层)","ExpMin":129998801,"ExpMax":169998780,"Awards":[10008,10009],"Counts":[233,7],"NeedType":[15006,3],"Monsters":[71053]},"57":{"ID":57,"Name":"大乘期(三层)","ExpMin":169998781,"ExpMax":219998760,"Awards":[10008,10009],"Counts":[234,7],"NeedType":[15006,4],"Monsters":[71054]},"58":{"ID":58,"Name":"大乘期(四层)","ExpMin":219998761,"ExpMax":289998740,"Awards":[10008,10009],"Counts":[235,7],"NeedType":[15006,5],"Monsters":[71055]},"59":{"ID":59,"Name":"大乘期(五层)","ExpMin":289998741,"ExpMax":379998720,"Awards":[10008,10009],"Counts":[236,7],"NeedType":[15006,6],"Monsters":[71056]},"60":{"ID":60,"Name":"大乘期(六层)","ExpMin":379998721,"ExpMax":489998700,"Awards":[10008,10009],"Counts":[237,7],"NeedType":[15006,7],"Monsters":[71057]},"61":{"ID":61,"Name":"大乘期(七层)","ExpMin":489998701,"ExpMax":629998680,"Awards":[10008,10009],"Counts":[238,7],"NeedType":[15006,8],"Monsters":[71058]},"62":{"ID":62,"Name":"大乘期(八层)","ExpMin":629998681,"ExpMax":799998660,"Awards":[10008,10009],"Counts":[239,7],"NeedType":[15006,9],"Monsters":[71059]},"63":{"ID":63,"Name":"大乘期(九层)","ExpMin":799998661,"ExpMax":999998640,"Awards":[10008,10009],"Counts":[240,7],"NeedType":[15007,1],"Monsters":[71061]},"64":{"ID":64,"Name":"渡劫期(一层)","ExpMin":999998641,"ExpMax":1299998620,"Awards":[10008,10009],"Counts":[309,8],"NeedType":[15007,2],"Monsters":[71062]},"65":{"ID":65,"Name":"渡劫期(二层)","ExpMin":1299998621,"ExpMax":1699998600,"Awards":[10008,10009],"Counts":[310,8],"NeedType":[15007,3],"Monsters":[71063]},"66":{"ID":66,"Name":"渡劫期(三层)","ExpMin":1699998601,"ExpMax":2199998460,"Awards":[10008,10009],"Counts":[311,8],"NeedType":[15007,4],"Monsters":[71064]},"67":{"ID":67,"Name":"渡劫期(四层)","ExpMin":2199998460,"ExpMax":2899998460,"Awards":[10008,10009],"Counts":[312,8],"NeedType":[15007,5],"Monsters":[71065]},"68":{"ID":68,"Name":"渡劫期(五层)","ExpMin":2899998460,"ExpMax":3799998460,"Awards":[10008,10009],"Counts":[313,8],"NeedType":[15007,6],"Monsters":[71066]},"69":{"ID":69,"Name":"渡劫期(六层)","ExpMin":3799998460,"ExpMax":4899998720,"Awards":[10008,10009],"Counts":[314,8],"NeedType":[15007,7],"Monsters":[71067]},"70":{"ID":70,"Name":"渡劫期(七层)","ExpMin":4899998720,"ExpMax":6299998720,"Awards":[10008,10009],"Counts":[315,8],"NeedType":[15007,8],"Monsters":[71068]},"71":{"ID":71,"Name":"渡劫期(八层)","ExpMin":6299998720,"ExpMax":7999998460,"Awards":[10008,10009],"Counts":[316,8],"NeedType":[15007,9],"Monsters":[71069]},"72":{"ID":72,"Name":"渡劫期(九层)","ExpMin":7999998460,"ExpMax":9999998000,"Awards":[10008,10009],"Counts":[317,8],"NeedType":[15008,1],"Monsters":[71071]},"73":{"ID":73,"Name":"真仙初期","ExpMin":9999998000,"ExpMax":12199998500,"Awards":[10008,10009],"Counts":[320,9],"NeedType":[15008,2],"Monsters":[71072]},"74":{"ID":74,"Name":"真仙中期","ExpMin":12199998500,"ExpMax":14619998200,"Awards":[10008,10009],"Counts":[320,9],"NeedType":[15008,3],"Monsters":[71073]},"75":{"ID":75,"Name":"真仙后期","ExpMin":14619998200,"ExpMax":17281998800,"Awards":[10008,10009],"Counts":[320,9],"NeedType":[15008,4],"Monsters":[71074]},"76":{"ID":76,"Name":"真仙圆满","ExpMin":17281998800,"ExpMax":20210198500,"Awards":[10008,10009],"Counts":[320,9],"NeedType":[15008,5],"Monsters":[71075]}}}